[{"DownloadCount":738,"UnixTimestamp":1651979485},{"DownloadCount":737,"UnixTimestamp":1651974475},{"DownloadCount":736,"UnixTimestamp":1651952392},{"DownloadCount":735,"UnixTimestamp":1651944498},{"DownloadCount":733,"UnixTimestamp":1651943213},{"DownloadCount":730,"UnixTimestamp":1651942248},{"DownloadCount":729,"UnixTimestamp":1651940433},{"DownloadCount":728,"UnixTimestamp":1651923995},{"DownloadCount":727,"UnixTimestamp":1651921355},{"DownloadCount":726,"UnixTimestamp":1651803989},{"DownloadCount":725,"UnixTimestamp":1651800529},{"DownloadCount":724,"UnixTimestamp":1651791151},{"DownloadCount":723,"UnixTimestamp":1651780562},{"DownloadCount":722,"UnixTimestamp":1651652371},{"DownloadCount":721,"UnixTimestamp":1651636735},{"DownloadCount":720,"UnixTimestamp":1651603037},{"DownloadCount":719,"UnixTimestamp":1651580547},{"DownloadCount":718,"UnixTimestamp":1651532127},{"DownloadCount":717,"UnixTimestamp":1651481288},{"DownloadCount":716,"UnixTimestamp":1651480176},{"DownloadCount":715,"UnixTimestamp":1651476820},{"DownloadCount":714,"UnixTimestamp":1651463369},{"DownloadCount":713,"UnixTimestamp":1651427128},{"DownloadCount":712,"UnixTimestamp":1651399402},{"DownloadCount":711,"UnixTimestamp":1651398977},{"DownloadCount":710,"UnixTimestamp":1651376981},{"DownloadCount":709,"UnixTimestamp":1651360527},{"DownloadCount":708,"UnixTimestamp":1651334588},{"DownloadCount":707,"UnixTimestamp":1651328306},{"DownloadCount":706,"UnixTimestamp":1651318231},{"DownloadCount":705,"UnixTimestamp":1651312936},{"DownloadCount":704,"UnixTimestamp":1651281716},{"DownloadCount":703,"UnixTimestamp":1651264539},{"DownloadCount":702,"UnixTimestamp":1651253497},{"DownloadCount":701,"UnixTimestamp":1651243594},{"DownloadCount":700,"UnixTimestamp":1651237162},{"DownloadCount":699,"UnixTimestamp":1651224103},{"DownloadCount":698,"UnixTimestamp":1651186491},{"DownloadCount":697,"UnixTimestamp":1651089138},{"DownloadCount":696,"UnixTimestamp":1651022623},{"DownloadCount":695,"UnixTimestamp":1651015467},{"DownloadCount":694,"UnixTimestamp":1651014248},{"DownloadCount":693,"UnixTimestamp":1650997824},{"DownloadCount":692,"UnixTimestamp":1650963334},{"DownloadCount":691,"UnixTimestamp":1650930459},{"DownloadCount":690,"UnixTimestamp":1650921545},{"DownloadCount":689,"UnixTimestamp":1650917022},{"DownloadCount":688,"UnixTimestamp":1650902369},{"DownloadCount":687,"UnixTimestamp":1650883284},{"DownloadCount":686,"UnixTimestamp":1650835761},{"DownloadCount":685,"UnixTimestamp":1650834800},{"DownloadCount":682,"UnixTimestamp":1650834020},{"DownloadCount":681,"UnixTimestamp":1650829219},{"DownloadCount":680,"UnixTimestamp":1650814492},{"DownloadCount":679,"UnixTimestamp":1650808491},{"DownloadCount":678,"UnixTimestamp":1650804511},{"DownloadCount":677,"UnixTimestamp":1650742074},{"DownloadCount":676,"UnixTimestamp":1650685699},{"DownloadCount":675,"UnixTimestamp":1650668119},{"DownloadCount":674,"UnixTimestamp":1650624007},{"DownloadCount":673,"UnixTimestamp":1650568064},{"DownloadCount":673,"UnixTimestamp":1650568064},{"DownloadCount":673,"UnixTimestamp":1650566781},{"DownloadCount":672,"UnixTimestamp":1650561443},{"DownloadCount":671,"UnixTimestamp":1650520807},{"DownloadCount":670,"UnixTimestamp":1650510988},{"DownloadCount":669,"UnixTimestamp":1650428023},{"DownloadCount":668,"UnixTimestamp":1650417347},{"DownloadCount":667,"UnixTimestamp":1650408299},{"DownloadCount":665,"UnixTimestamp":1650396926},{"DownloadCount":664,"UnixTimestamp":1650390717},{"DownloadCount":663,"UnixTimestamp":1650368336},{"DownloadCount":662,"UnixTimestamp":1650367778},{"DownloadCount":661,"UnixTimestamp":1650337075},{"DownloadCount":660,"UnixTimestamp":1650330048},{"DownloadCount":659,"UnixTimestamp":1650318548},{"DownloadCount":658,"UnixTimestamp":1650293917},{"DownloadCount":657,"UnixTimestamp":1650286724},{"DownloadCount":655,"UnixTimestamp":1650266322},{"DownloadCount":654,"UnixTimestamp":1650263759},{"DownloadCount":654,"UnixTimestamp":1650263759},{"DownloadCount":654,"UnixTimestamp":1650260949},{"DownloadCount":653,"UnixTimestamp":1650232669},{"DownloadCount":652,"UnixTimestamp":1650227301},{"DownloadCount":651,"UnixTimestamp":1650221746},{"DownloadCount":650,"UnixTimestamp":1650199984},{"DownloadCount":649,"UnixTimestamp":1650192166},{"DownloadCount":648,"UnixTimestamp":1650159714},{"DownloadCount":647,"UnixTimestamp":1650153242},{"DownloadCount":646,"UnixTimestamp":1650130370},{"DownloadCount":645,"UnixTimestamp":1650127171},{"DownloadCount":644,"UnixTimestamp":1650105947},{"DownloadCount":643,"UnixTimestamp":1650105288},{"DownloadCount":642,"UnixTimestamp":1650104135},{"DownloadCount":641,"UnixTimestamp":1650043236},{"DownloadCount":640,"UnixTimestamp":1650017263},{"DownloadCount":639,"UnixTimestamp":1649989799},{"DownloadCount":638,"UnixTimestamp":1649972713},{"DownloadCount":637,"UnixTimestamp":1649970514},{"DownloadCount":636,"UnixTimestamp":1649941086},{"DownloadCount":635,"UnixTimestamp":1649936957},{"DownloadCount":634,"UnixTimestamp":1649908750},{"DownloadCount":633,"UnixTimestamp":1649896964},{"DownloadCount":632,"UnixTimestamp":1649888976},{"DownloadCount":631,"UnixTimestamp":1649873458},{"DownloadCount":630,"UnixTimestamp":1649836935},{"DownloadCount":629,"UnixTimestamp":1649825337},{"DownloadCount":628,"UnixTimestamp":1649792671},{"DownloadCount":627,"UnixTimestamp":1649788657},{"DownloadCount":626,"UnixTimestamp":1649784553},{"DownloadCount":625,"UnixTimestamp":1649776747},{"DownloadCount":624,"UnixTimestamp":1649756329},{"DownloadCount":623,"UnixTimestamp":1649755692},{"DownloadCount":622,"UnixTimestamp":1649733840},{"DownloadCount":621,"UnixTimestamp":1649731499},{"DownloadCount":620,"UnixTimestamp":1649725133},{"DownloadCount":619,"UnixTimestamp":1649721557},{"DownloadCount":618,"UnixTimestamp":1649719260},{"DownloadCount":617,"UnixTimestamp":1649686862},{"DownloadCount":616,"UnixTimestamp":1649649227},{"DownloadCount":615,"UnixTimestamp":1649643751},{"DownloadCount":614,"UnixTimestamp":1649614410},{"DownloadCount":613,"UnixTimestamp":1649591580},{"DownloadCount":612,"UnixTimestamp":1649567743},{"DownloadCount":611,"UnixTimestamp":1649566778},{"DownloadCount":610,"UnixTimestamp":1649535428},{"DownloadCount":609,"UnixTimestamp":1649518596},{"DownloadCount":608,"UnixTimestamp":1649505510},{"DownloadCount":607,"UnixTimestamp":1649499257},{"DownloadCount":606,"UnixTimestamp":1649496506},{"DownloadCount":605,"UnixTimestamp":1649455857},{"DownloadCount":604,"UnixTimestamp":1649453752},{"DownloadCount":603,"UnixTimestamp":1649451027},{"DownloadCount":602,"UnixTimestamp":1649450038},{"DownloadCount":601,"UnixTimestamp":1649415148},{"DownloadCount":600,"UnixTimestamp":1649396433},{"DownloadCount":599,"UnixTimestamp":1649384559},{"DownloadCount":598,"UnixTimestamp":1649360304},{"DownloadCount":597,"UnixTimestamp":1649309852},{"DownloadCount":597,"UnixTimestamp":1649309852},{"DownloadCount":597,"UnixTimestamp":1649294789},{"DownloadCount":595,"UnixTimestamp":1649277144},{"DownloadCount":593,"UnixTimestamp":1649240389},{"DownloadCount":592,"UnixTimestamp":1649220272},{"DownloadCount":591,"UnixTimestamp":1649182458},{"DownloadCount":590,"UnixTimestamp":1649169369},{"DownloadCount":589,"UnixTimestamp":1649127972},{"DownloadCount":588,"UnixTimestamp":1649119483},{"DownloadCount":587,"UnixTimestamp":1649103444},{"DownloadCount":586,"UnixTimestamp":1649096268},{"DownloadCount":585,"UnixTimestamp":1649091256},{"DownloadCount":584,"UnixTimestamp":1649077082},{"DownloadCount":583,"UnixTimestamp":1649046513},{"DownloadCount":582,"UnixTimestamp":1649026664},{"DownloadCount":581,"UnixTimestamp":1649026132},{"DownloadCount":580,"UnixTimestamp":1648977042},{"DownloadCount":579,"UnixTimestamp":1648964913},{"DownloadCount":578,"UnixTimestamp":1648931626},{"DownloadCount":577,"UnixTimestamp":1648923740},{"DownloadCount":576,"UnixTimestamp":1648909097},{"DownloadCount":574,"UnixTimestamp":1648865649},{"DownloadCount":573,"UnixTimestamp":1648859421},{"DownloadCount":572,"UnixTimestamp":1648845798},{"DownloadCount":571,"UnixTimestamp":1648842932},{"DownloadCount":570,"UnixTimestamp":1648731809},{"DownloadCount":568,"UnixTimestamp":1648677495},{"DownloadCount":567,"UnixTimestamp":1648675968},{"DownloadCount":566,"UnixTimestamp":1648663979},{"DownloadCount":565,"UnixTimestamp":1648602118},{"DownloadCount":564,"UnixTimestamp":1648594857},{"DownloadCount":563,"UnixTimestamp":1648570892},{"DownloadCount":562,"UnixTimestamp":1648515135},{"DownloadCount":561,"UnixTimestamp":1648510295},{"DownloadCount":560,"UnixTimestamp":1648506037},{"DownloadCount":559,"UnixTimestamp":1648496488},{"DownloadCount":558,"UnixTimestamp":1648495710},{"DownloadCount":557,"UnixTimestamp":1648490223},{"DownloadCount":556,"UnixTimestamp":1648489084},{"DownloadCount":555,"UnixTimestamp":1648406656},{"DownloadCount":554,"UnixTimestamp":1648392341},{"DownloadCount":553,"UnixTimestamp":1648343033},{"DownloadCount":552,"UnixTimestamp":1648333026},{"DownloadCount":551,"UnixTimestamp":1648322707},{"DownloadCount":550,"UnixTimestamp":1648250946},{"DownloadCount":549,"UnixTimestamp":1648249175},{"DownloadCount":548,"UnixTimestamp":1648234312},{"DownloadCount":547,"UnixTimestamp":1648227596},{"DownloadCount":546,"UnixTimestamp":1648201815},{"DownloadCount":545,"UnixTimestamp":1648121827},{"DownloadCount":544,"UnixTimestamp":1648087347},{"DownloadCount":543,"UnixTimestamp":1648072439},{"DownloadCount":542,"UnixTimestamp":1648064726},{"DownloadCount":541,"UnixTimestamp":1648043669},{"DownloadCount":540,"UnixTimestamp":1648017203},{"DownloadCount":539,"UnixTimestamp":1647995561},{"DownloadCount":538,"UnixTimestamp":1647981710},{"DownloadCount":537,"UnixTimestamp":1647981166},{"DownloadCount":536,"UnixTimestamp":1647970786},{"DownloadCount":535,"UnixTimestamp":1647969938},{"DownloadCount":534,"UnixTimestamp":1647933848},{"DownloadCount":533,"UnixTimestamp":1647915222},{"DownloadCount":531,"UnixTimestamp":1647890454},{"DownloadCount":529,"UnixTimestamp":1647888645},{"DownloadCount":528,"UnixTimestamp":1647852743},{"DownloadCount":527,"UnixTimestamp":1647842167},{"DownloadCount":526,"UnixTimestamp":1647841441},{"DownloadCount":525,"UnixTimestamp":1647840704},{"DownloadCount":524,"UnixTimestamp":1647837505},{"DownloadCount":523,"UnixTimestamp":1647831622},{"DownloadCount":521,"UnixTimestamp":1647828921},{"DownloadCount":520,"UnixTimestamp":1647823493},{"DownloadCount":519,"UnixTimestamp":1647804770},{"DownloadCount":518,"UnixTimestamp":1647780356},{"DownloadCount":517,"UnixTimestamp":1647768351},{"DownloadCount":516,"UnixTimestamp":1647756059},{"DownloadCount":515,"UnixTimestamp":1647747069},{"DownloadCount":514,"UnixTimestamp":1647741096},{"DownloadCount":513,"UnixTimestamp":1647698311},{"DownloadCount":512,"UnixTimestamp":1647661580},{"DownloadCount":511,"UnixTimestamp":1647646646},{"DownloadCount":510,"UnixTimestamp":1647637107},{"DownloadCount":509,"UnixTimestamp":1647571153},{"DownloadCount":508,"UnixTimestamp":1647548421},{"DownloadCount":507,"UnixTimestamp":1647542877},{"DownloadCount":506,"UnixTimestamp":1647525014},{"DownloadCount":505,"UnixTimestamp":1647469731},{"DownloadCount":504,"UnixTimestamp":1647455802},{"DownloadCount":503,"UnixTimestamp":1647444526},{"DownloadCount":502,"UnixTimestamp":1647386810},{"DownloadCount":501,"UnixTimestamp":1647385027},{"DownloadCount":500,"UnixTimestamp":1647370775},{"DownloadCount":499,"UnixTimestamp":1647366421},{"DownloadCount":499,"UnixTimestamp":1647366421},{"DownloadCount":499,"UnixTimestamp":1647365001},{"DownloadCount":498,"UnixTimestamp":1647327092},{"DownloadCount":496,"UnixTimestamp":1647297577},{"DownloadCount":495,"UnixTimestamp":1647297026},{"DownloadCount":494,"UnixTimestamp":1647217925},{"DownloadCount":493,"UnixTimestamp":1647198863},{"DownloadCount":492,"UnixTimestamp":1647177743},{"DownloadCount":491,"UnixTimestamp":1647171853},{"DownloadCount":489,"UnixTimestamp":1647161064},{"DownloadCount":488,"UnixTimestamp":1647148276},{"DownloadCount":487,"UnixTimestamp":1647146416},{"DownloadCount":486,"UnixTimestamp":1647142673},{"DownloadCount":485,"UnixTimestamp":1647113552},{"DownloadCount":484,"UnixTimestamp":1647104890},{"DownloadCount":483,"UnixTimestamp":1647104191},{"DownloadCount":482,"UnixTimestamp":1647103122},{"DownloadCount":481,"UnixTimestamp":1647084185},{"DownloadCount":480,"UnixTimestamp":1647075430},{"DownloadCount":479,"UnixTimestamp":1647056681},{"DownloadCount":478,"UnixTimestamp":1647053779},{"DownloadCount":477,"UnixTimestamp":1647053254},{"DownloadCount":476,"UnixTimestamp":1647045563},{"DownloadCount":475,"UnixTimestamp":1647039334},{"DownloadCount":474,"UnixTimestamp":1647038589},{"DownloadCount":473,"UnixTimestamp":1647035084},{"DownloadCount":472,"UnixTimestamp":1647027716},{"DownloadCount":471,"UnixTimestamp":1647026033},{"DownloadCount":470,"UnixTimestamp":1647025233},{"DownloadCount":469,"UnixTimestamp":1647004300},{"DownloadCount":467,"UnixTimestamp":1646968923},{"DownloadCount":466,"UnixTimestamp":1646943372},{"DownloadCount":465,"UnixTimestamp":1646938144},{"DownloadCount":464,"UnixTimestamp":1646937506},{"DownloadCount":463,"UnixTimestamp":1646931157},{"DownloadCount":462,"UnixTimestamp":1646902142},{"DownloadCount":461,"UnixTimestamp":1646870004},{"DownloadCount":460,"UnixTimestamp":1646864866},{"DownloadCount":459,"UnixTimestamp":1646802888},{"DownloadCount":458,"UnixTimestamp":1646800969},{"DownloadCount":457,"UnixTimestamp":1646791517},{"DownloadCount":456,"UnixTimestamp":1646767412},{"DownloadCount":455,"UnixTimestamp":1646763579},{"DownloadCount":454,"UnixTimestamp":1646749470},{"DownloadCount":453,"UnixTimestamp":1646722794},{"DownloadCount":452,"UnixTimestamp":1646695940},{"DownloadCount":451,"UnixTimestamp":1646692132},{"DownloadCount":450,"UnixTimestamp":1646681360},{"DownloadCount":449,"UnixTimestamp":1646662253},{"DownloadCount":448,"UnixTimestamp":1646648522},{"DownloadCount":447,"UnixTimestamp":1646642077},{"DownloadCount":446,"UnixTimestamp":1646640953},{"DownloadCount":445,"UnixTimestamp":1646628674},{"DownloadCount":444,"UnixTimestamp":1646625089},{"DownloadCount":442,"UnixTimestamp":1646598521},{"DownloadCount":441,"UnixTimestamp":1646589604},{"DownloadCount":440,"UnixTimestamp":1646587706},{"DownloadCount":439,"UnixTimestamp":1646578492},{"DownloadCount":438,"UnixTimestamp":1646558080},{"DownloadCount":437,"UnixTimestamp":1646539160},{"DownloadCount":436,"UnixTimestamp":1646528391},{"DownloadCount":434,"UnixTimestamp":1646524777},{"DownloadCount":433,"UnixTimestamp":1646521194},{"DownloadCount":432,"UnixTimestamp":1646513704},{"DownloadCount":431,"UnixTimestamp":1646501457},{"DownloadCount":430,"UnixTimestamp":1646493702},{"DownloadCount":429,"UnixTimestamp":1646492817},{"DownloadCount":426,"UnixTimestamp":1646466020},{"DownloadCount":425,"UnixTimestamp":1646458150},{"DownloadCount":424,"UnixTimestamp":1646441839},{"DownloadCount":423,"UnixTimestamp":1646430806},{"DownloadCount":422,"UnixTimestamp":1646429231},{"DownloadCount":421,"UnixTimestamp":1646426506},{"DownloadCount":419,"UnixTimestamp":1646339312},{"DownloadCount":418,"UnixTimestamp":1646284249},{"DownloadCount":417,"UnixTimestamp":1646279543},{"DownloadCount":416,"UnixTimestamp":1646261049},{"DownloadCount":415,"UnixTimestamp":1646246920},{"DownloadCount":414,"UnixTimestamp":1646190533},{"DownloadCount":413,"UnixTimestamp":1646175629},{"DownloadCount":412,"UnixTimestamp":1646171850},{"DownloadCount":411,"UnixTimestamp":1646141116},{"DownloadCount":410,"UnixTimestamp":1646063631},{"DownloadCount":409,"UnixTimestamp":1646046529},{"DownloadCount":408,"UnixTimestamp":1646024423},{"DownloadCount":407,"UnixTimestamp":1646010126},{"DownloadCount":406,"UnixTimestamp":1646003678},{"DownloadCount":405,"UnixTimestamp":1645992743},{"DownloadCount":404,"UnixTimestamp":1645950675},{"DownloadCount":403,"UnixTimestamp":1645944564},{"DownloadCount":402,"UnixTimestamp":1645939227},{"DownloadCount":401,"UnixTimestamp":1645904028},{"DownloadCount":399,"UnixTimestamp":1645891868},{"DownloadCount":398,"UnixTimestamp":1645846974},{"DownloadCount":397,"UnixTimestamp":1645844541},{"DownloadCount":396,"UnixTimestamp":1645839837},{"DownloadCount":395,"UnixTimestamp":1645825899},{"DownloadCount":394,"UnixTimestamp":1645802663},{"DownloadCount":393,"UnixTimestamp":1645800946},{"DownloadCount":392,"UnixTimestamp":1645771816},{"DownloadCount":391,"UnixTimestamp":1645759682},{"DownloadCount":390,"UnixTimestamp":1645757275},{"DownloadCount":389,"UnixTimestamp":1645715720},{"DownloadCount":387,"UnixTimestamp":1645677134},{"DownloadCount":386,"UnixTimestamp":1645672290},{"DownloadCount":385,"UnixTimestamp":1645669656},{"DownloadCount":384,"UnixTimestamp":1645667135},{"DownloadCount":382,"UnixTimestamp":1645660536},{"DownloadCount":381,"UnixTimestamp":1645659431},{"DownloadCount":380,"UnixTimestamp":1645658861},{"DownloadCount":379,"UnixTimestamp":1645657071},{"DownloadCount":378,"UnixTimestamp":1645599297},{"DownloadCount":377,"UnixTimestamp":1645586761},{"DownloadCount":376,"UnixTimestamp":1645581067},{"DownloadCount":375,"UnixTimestamp":1645572563},{"DownloadCount":374,"UnixTimestamp":1645506488},{"DownloadCount":373,"UnixTimestamp":1645505442},{"DownloadCount":372,"UnixTimestamp":1645486076},{"DownloadCount":371,"UnixTimestamp":1645481226},{"DownloadCount":370,"UnixTimestamp":1645458585},{"DownloadCount":369,"UnixTimestamp":1645458228},{"DownloadCount":368,"UnixTimestamp":1645414021},{"DownloadCount":367,"UnixTimestamp":1645390374},{"DownloadCount":366,"UnixTimestamp":1645388817},{"DownloadCount":365,"UnixTimestamp":1645337788},{"DownloadCount":364,"UnixTimestamp":1645331964},{"DownloadCount":363,"UnixTimestamp":1645324023},{"DownloadCount":362,"UnixTimestamp":1645315138},{"DownloadCount":361,"UnixTimestamp":1645311482},{"DownloadCount":360,"UnixTimestamp":1645303604},{"DownloadCount":359,"UnixTimestamp":1645299868},{"DownloadCount":358,"UnixTimestamp":1645287503},{"DownloadCount":357,"UnixTimestamp":1645277190},{"DownloadCount":356,"UnixTimestamp":1645272536},{"DownloadCount":355,"UnixTimestamp":1645256234},{"DownloadCount":354,"UnixTimestamp":1645241436},{"DownloadCount":353,"UnixTimestamp":1645235587},{"DownloadCount":352,"UnixTimestamp":1645232160},{"DownloadCount":350,"UnixTimestamp":1645224450},{"DownloadCount":349,"UnixTimestamp":1645222084},{"DownloadCount":348,"UnixTimestamp":1645217976},{"DownloadCount":347,"UnixTimestamp":1645215033},{"DownloadCount":345,"UnixTimestamp":1645209445},{"DownloadCount":344,"UnixTimestamp":1645200978},{"DownloadCount":343,"UnixTimestamp":1645195129},{"DownloadCount":342,"UnixTimestamp":1645190812},{"DownloadCount":341,"UnixTimestamp":1645188741},{"DownloadCount":340,"UnixTimestamp":1645156470},{"DownloadCount":339,"UnixTimestamp":1645144311},{"DownloadCount":337,"UnixTimestamp":1645131612},{"DownloadCount":336,"UnixTimestamp":1645130883},{"DownloadCount":335,"UnixTimestamp":1645121323},{"DownloadCount":334,"UnixTimestamp":1645109775},{"DownloadCount":333,"UnixTimestamp":1645104212},{"DownloadCount":332,"UnixTimestamp":1645087413},{"DownloadCount":331,"UnixTimestamp":1645066393},{"DownloadCount":330,"UnixTimestamp":1645061852},{"DownloadCount":329,"UnixTimestamp":1645050305},{"DownloadCount":328,"UnixTimestamp":1645042445},{"DownloadCount":327,"UnixTimestamp":1645041208},{"DownloadCount":326,"UnixTimestamp":1645035625},{"DownloadCount":325,"UnixTimestamp":1645023031},{"DownloadCount":324,"UnixTimestamp":1645012473},{"DownloadCount":323,"UnixTimestamp":1645012124},{"DownloadCount":322,"UnixTimestamp":1645000203},{"DownloadCount":321,"UnixTimestamp":1644993389},{"DownloadCount":320,"UnixTimestamp":1644986133},{"DownloadCount":318,"UnixTimestamp":1644984680},{"DownloadCount":317,"UnixTimestamp":1644983852},{"DownloadCount":316,"UnixTimestamp":1644983484},{"DownloadCount":315,"UnixTimestamp":1644981313},{"DownloadCount":314,"UnixTimestamp":1644979218},{"DownloadCount":313,"UnixTimestamp":1644961423},{"DownloadCount":312,"UnixTimestamp":1644957537},{"DownloadCount":311,"UnixTimestamp":1644956406},{"DownloadCount":310,"UnixTimestamp":1644953814},{"DownloadCount":309,"UnixTimestamp":1644950044},{"DownloadCount":308,"UnixTimestamp":1644945205},{"DownloadCount":307,"UnixTimestamp":1644921740},{"DownloadCount":306,"UnixTimestamp":1644909370},{"DownloadCount":305,"UnixTimestamp":1644903042},{"DownloadCount":304,"UnixTimestamp":1644900092},{"DownloadCount":303,"UnixTimestamp":1644893766},{"DownloadCount":302,"UnixTimestamp":1644893232},{"DownloadCount":301,"UnixTimestamp":1644880809},{"DownloadCount":300,"UnixTimestamp":1644876031},{"DownloadCount":299,"UnixTimestamp":1644873827},{"DownloadCount":298,"UnixTimestamp":1644872155},{"DownloadCount":297,"UnixTimestamp":1644870634},{"DownloadCount":295,"UnixTimestamp":1644866104},{"DownloadCount":294,"UnixTimestamp":1644865252},{"DownloadCount":293,"UnixTimestamp":1644864912},{"DownloadCount":292,"UnixTimestamp":1644864128},{"DownloadCount":289,"UnixTimestamp":1644863401},{"DownloadCount":288,"UnixTimestamp":1644834508},{"DownloadCount":287,"UnixTimestamp":1644828289},{"DownloadCount":286,"UnixTimestamp":1644824947},{"DownloadCount":285,"UnixTimestamp":1644821490},{"DownloadCount":283,"UnixTimestamp":1644818193},{"DownloadCount":282,"UnixTimestamp":1644804870},{"DownloadCount":281,"UnixTimestamp":1644799816},{"DownloadCount":280,"UnixTimestamp":1644790388},{"DownloadCount":279,"UnixTimestamp":1644781329},{"DownloadCount":278,"UnixTimestamp":1644780962},{"DownloadCount":277,"UnixTimestamp":1644779157},{"DownloadCount":276,"UnixTimestamp":1644776412},{"DownloadCount":275,"UnixTimestamp":1644762882},{"DownloadCount":274,"UnixTimestamp":1644757881},{"DownloadCount":272,"UnixTimestamp":1644746438},{"DownloadCount":271,"UnixTimestamp":1644738463},{"DownloadCount":270,"UnixTimestamp":1644737726},{"DownloadCount":269,"UnixTimestamp":1644735451},{"DownloadCount":268,"UnixTimestamp":1644733965},{"DownloadCount":267,"UnixTimestamp":1644728826},{"DownloadCount":266,"UnixTimestamp":1644720190},{"DownloadCount":265,"UnixTimestamp":1644718771},{"DownloadCount":263,"UnixTimestamp":1644716499},{"DownloadCount":261,"UnixTimestamp":1644712049},{"DownloadCount":259,"UnixTimestamp":1644707435},{"DownloadCount":258,"UnixTimestamp":1644704024},{"DownloadCount":257,"UnixTimestamp":1644698119},{"DownloadCount":256,"UnixTimestamp":1644697673},{"DownloadCount":255,"UnixTimestamp":1644696798},{"DownloadCount":254,"UnixTimestamp":1644689605},{"DownloadCount":253,"UnixTimestamp":1644688343},{"DownloadCount":252,"UnixTimestamp":1644683482},{"DownloadCount":251,"UnixTimestamp":1644676396},{"DownloadCount":250,"UnixTimestamp":1644673402},{"DownloadCount":249,"UnixTimestamp":1644671458},{"DownloadCount":248,"UnixTimestamp":1644665162},{"DownloadCount":247,"UnixTimestamp":1644643273},{"DownloadCount":246,"UnixTimestamp":1644636861},{"DownloadCount":245,"UnixTimestamp":1644636385},{"DownloadCount":244,"UnixTimestamp":1644632793},{"DownloadCount":243,"UnixTimestamp":1644630320},{"DownloadCount":241,"UnixTimestamp":1644625873},{"DownloadCount":240,"UnixTimestamp":1644620790},{"DownloadCount":239,"UnixTimestamp":1644620183},{"DownloadCount":238,"UnixTimestamp":1644619823},{"DownloadCount":237,"UnixTimestamp":1644618240},{"DownloadCount":236,"UnixTimestamp":1644615915},{"DownloadCount":235,"UnixTimestamp":1644611415},{"DownloadCount":233,"UnixTimestamp":1644607821},{"DownloadCount":232,"UnixTimestamp":1644606388},{"DownloadCount":231,"UnixTimestamp":1644605089},{"DownloadCount":230,"UnixTimestamp":1644595951},{"DownloadCount":229,"UnixTimestamp":1644593885},{"DownloadCount":228,"UnixTimestamp":1644592230},{"DownloadCount":227,"UnixTimestamp":1644588940},{"DownloadCount":226,"UnixTimestamp":1644583528},{"DownloadCount":225,"UnixTimestamp":1644572057},{"DownloadCount":224,"UnixTimestamp":1644568138},{"DownloadCount":223,"UnixTimestamp":1644553079},{"DownloadCount":222,"UnixTimestamp":1644551961},{"DownloadCount":221,"UnixTimestamp":1644544917},{"DownloadCount":220,"UnixTimestamp":1644541220},{"DownloadCount":215,"UnixTimestamp":1644536872},{"DownloadCount":214,"UnixTimestamp":1644535671},{"DownloadCount":213,"UnixTimestamp":1644526195},{"DownloadCount":212,"UnixTimestamp":1644524373},{"DownloadCount":211,"UnixTimestamp":1644520231},{"DownloadCount":210,"UnixTimestamp":1644519656},{"DownloadCount":209,"UnixTimestamp":1644515106},{"DownloadCount":208,"UnixTimestamp":1644511872},{"DownloadCount":207,"UnixTimestamp":1644508886},{"DownloadCount":206,"UnixTimestamp":1644499277},{"DownloadCount":205,"UnixTimestamp":1644487867},{"DownloadCount":204,"UnixTimestamp":1644470483},{"DownloadCount":202,"UnixTimestamp":1644468982},{"DownloadCount":201,"UnixTimestamp":1644468613},{"DownloadCount":200,"UnixTimestamp":1644459388},{"DownloadCount":199,"UnixTimestamp":1644457437},{"DownloadCount":198,"UnixTimestamp":1644451041},{"DownloadCount":197,"UnixTimestamp":1644438275},{"DownloadCount":196,"UnixTimestamp":1644427972},{"DownloadCount":195,"UnixTimestamp":1644424637},{"DownloadCount":194,"UnixTimestamp":1644419764},{"DownloadCount":193,"UnixTimestamp":1644416961},{"DownloadCount":192,"UnixTimestamp":1644386373},{"DownloadCount":191,"UnixTimestamp":1644384902},{"DownloadCount":190,"UnixTimestamp":1644381469},{"DownloadCount":189,"UnixTimestamp":1644380107},{"DownloadCount":188,"UnixTimestamp":1644377543},{"DownloadCount":187,"UnixTimestamp":1644373388},{"DownloadCount":186,"UnixTimestamp":1644371324},{"DownloadCount":184,"UnixTimestamp":1644363548},{"DownloadCount":182,"UnixTimestamp":1644360547},{"DownloadCount":181,"UnixTimestamp":1644359370},{"DownloadCount":180,"UnixTimestamp":1644357664},{"DownloadCount":179,"UnixTimestamp":1644354744},{"DownloadCount":178,"UnixTimestamp":1644331385},{"DownloadCount":177,"UnixTimestamp":1644294497},{"DownloadCount":176,"UnixTimestamp":1644290925},{"DownloadCount":175,"UnixTimestamp":1644286765},{"DownloadCount":173,"UnixTimestamp":1644284704},{"DownloadCount":172,"UnixTimestamp":1644276742},{"DownloadCount":171,"UnixTimestamp":1644267413},{"DownloadCount":170,"UnixTimestamp":1644266708},{"DownloadCount":169,"UnixTimestamp":1644265605},{"DownloadCount":168,"UnixTimestamp":1644261138},{"DownloadCount":167,"UnixTimestamp":1644254509},{"DownloadCount":165,"UnixTimestamp":1644248491},{"DownloadCount":164,"UnixTimestamp":1644246973},{"DownloadCount":163,"UnixTimestamp":1644243744},{"DownloadCount":162,"UnixTimestamp":1644236205},{"DownloadCount":161,"UnixTimestamp":1644231473},{"DownloadCount":160,"UnixTimestamp":1644225796},{"DownloadCount":159,"UnixTimestamp":1644222732},{"DownloadCount":158,"UnixTimestamp":1644215851},{"DownloadCount":157,"UnixTimestamp":1644214741},{"DownloadCount":156,"UnixTimestamp":1644211425},{"DownloadCount":155,"UnixTimestamp":1644203237},{"DownloadCount":154,"UnixTimestamp":1644202230},{"DownloadCount":153,"UnixTimestamp":1644190296},{"DownloadCount":152,"UnixTimestamp":1644189068},{"DownloadCount":151,"UnixTimestamp":1644187208},{"DownloadCount":150,"UnixTimestamp":1644186372},{"DownloadCount":149,"UnixTimestamp":1644177005},{"DownloadCount":148,"UnixTimestamp":1644176623},{"DownloadCount":147,"UnixTimestamp":1644174667},{"DownloadCount":146,"UnixTimestamp":1644173279},{"DownloadCount":145,"UnixTimestamp":1644172876},{"DownloadCount":144,"UnixTimestamp":1644169919},{"DownloadCount":143,"UnixTimestamp":1644168267},{"DownloadCount":141,"UnixTimestamp":1644166572},{"DownloadCount":139,"UnixTimestamp":1644165419},{"DownloadCount":138,"UnixTimestamp":1644161318},{"DownloadCount":137,"UnixTimestamp":1644160389},{"DownloadCount":136,"UnixTimestamp":1644158847},{"DownloadCount":135,"UnixTimestamp":1644157772},{"DownloadCount":134,"UnixTimestamp":1644151442},{"DownloadCount":133,"UnixTimestamp":1644145905},{"DownloadCount":132,"UnixTimestamp":1644144104},{"DownloadCount":131,"UnixTimestamp":1644137714},{"DownloadCount":130,"UnixTimestamp":1644133039},{"DownloadCount":129,"UnixTimestamp":1644129223},{"DownloadCount":128,"UnixTimestamp":1644128092},{"DownloadCount":127,"UnixTimestamp":1644127140},{"DownloadCount":126,"UnixTimestamp":1644126392},{"DownloadCount":125,"UnixTimestamp":1644125996},{"DownloadCount":123,"UnixTimestamp":1644121124},{"DownloadCount":122,"UnixTimestamp":1644118031},{"DownloadCount":121,"UnixTimestamp":1644112048},{"DownloadCount":118,"UnixTimestamp":1644107844},{"DownloadCount":117,"UnixTimestamp":1644104052},{"DownloadCount":116,"UnixTimestamp":1644100099},{"DownloadCount":115,"UnixTimestamp":1644098963},{"DownloadCount":114,"UnixTimestamp":1644096359},{"DownloadCount":113,"UnixTimestamp":1644092488},{"DownloadCount":111,"UnixTimestamp":1644091080},{"DownloadCount":110,"UnixTimestamp":1644084512},{"DownloadCount":109,"UnixTimestamp":1644074352},{"DownloadCount":108,"UnixTimestamp":1644052455},{"DownloadCount":107,"UnixTimestamp":1644051626},{"DownloadCount":106,"UnixTimestamp":1644049817},{"DownloadCount":104,"UnixTimestamp":1644039993},{"DownloadCount":102,"UnixTimestamp":1644036544},{"DownloadCount":101,"UnixTimestamp":1644035749},{"DownloadCount":100,"UnixTimestamp":1644034036},{"DownloadCount":99,"UnixTimestamp":1644030895},{"DownloadCount":98,"UnixTimestamp":1644028930},{"DownloadCount":97,"UnixTimestamp":1644028200},{"DownloadCount":96,"UnixTimestamp":1644026006},{"DownloadCount":95,"UnixTimestamp":1644024401},{"DownloadCount":94,"UnixTimestamp":1644021433},{"DownloadCount":92,"UnixTimestamp":1644018403},{"DownloadCount":91,"UnixTimestamp":1644016973},{"DownloadCount":90,"UnixTimestamp":1644015157},{"DownloadCount":89,"UnixTimestamp":1644014424},{"DownloadCount":88,"UnixTimestamp":1644013704},{"DownloadCount":87,"UnixTimestamp":1644010866},{"DownloadCount":86,"UnixTimestamp":1644010112},{"DownloadCount":85,"UnixTimestamp":1644009128},{"DownloadCount":84,"UnixTimestamp":1644005512},{"DownloadCount":83,"UnixTimestamp":1644001707},{"DownloadCount":82,"UnixTimestamp":1644000018},{"DownloadCount":81,"UnixTimestamp":1643999673},{"DownloadCount":80,"UnixTimestamp":1643994791},{"DownloadCount":79,"UnixTimestamp":1643990855},{"DownloadCount":77,"UnixTimestamp":1643990176},{"DownloadCount":76,"UnixTimestamp":1643989820},{"DownloadCount":74,"UnixTimestamp":1643988730},{"DownloadCount":73,"UnixTimestamp":1643985394},{"DownloadCount":72,"UnixTimestamp":1643983486},{"DownloadCount":71,"UnixTimestamp":1643973616},{"DownloadCount":70,"UnixTimestamp":1643971757},{"DownloadCount":69,"UnixTimestamp":1643967316},{"DownloadCount":68,"UnixTimestamp":1643958738},{"DownloadCount":67,"UnixTimestamp":1643956089},{"DownloadCount":66,"UnixTimestamp":1643952550},{"DownloadCount":64,"UnixTimestamp":1643948811},{"DownloadCount":61,"UnixTimestamp":1643944660},{"DownloadCount":60,"UnixTimestamp":1643943731},{"DownloadCount":59,"UnixTimestamp":1643943325},{"DownloadCount":57,"UnixTimestamp":1643942550},{"DownloadCount":56,"UnixTimestamp":1643940279},{"DownloadCount":55,"UnixTimestamp":1643936388},{"DownloadCount":54,"UnixTimestamp":1643932511},{"DownloadCount":53,"UnixTimestamp":1643930702},{"DownloadCount":52,"UnixTimestamp":1643930163},{"DownloadCount":50,"UnixTimestamp":1643923526},{"DownloadCount":49,"UnixTimestamp":1643922049},{"DownloadCount":48,"UnixTimestamp":1643917992},{"DownloadCount":46,"UnixTimestamp":1643917373},{"DownloadCount":45,"UnixTimestamp":1643910150},{"DownloadCount":44,"UnixTimestamp":1643909117},{"DownloadCount":43,"UnixTimestamp":1643899662},{"DownloadCount":42,"UnixTimestamp":1643895109},{"DownloadCount":41,"UnixTimestamp":1643894472},{"DownloadCount":40,"UnixTimestamp":1643887184},{"DownloadCount":39,"UnixTimestamp":1643870957},{"DownloadCount":38,"UnixTimestamp":1643868058},{"DownloadCount":37,"UnixTimestamp":1643867692},{"DownloadCount":36,"UnixTimestamp":1643867340},{"DownloadCount":35,"UnixTimestamp":1643856598},{"DownloadCount":34,"UnixTimestamp":1643854431},{"DownloadCount":29,"UnixTimestamp":1643852509},{"DownloadCount":27,"UnixTimestamp":1643849169},{"DownloadCount":25,"UnixTimestamp":1643846354},{"DownloadCount":24,"UnixTimestamp":1643845255},{"DownloadCount":23,"UnixTimestamp":1643844874},{"DownloadCount":22,"UnixTimestamp":1643844411},{"DownloadCount":21,"UnixTimestamp":1643843499},{"DownloadCount":20,"UnixTimestamp":1643841209},{"DownloadCount":19,"UnixTimestamp":1643840691},{"DownloadCount":18,"UnixTimestamp":1643838357},{"DownloadCount":17,"UnixTimestamp":1643837182},{"DownloadCount":16,"UnixTimestamp":1643836384},{"DownloadCount":15,"UnixTimestamp":1643835198},{"DownloadCount":14,"UnixTimestamp":1643834485},{"DownloadCount":13,"UnixTimestamp":1643827922},{"DownloadCount":12,"UnixTimestamp":1643826847},{"DownloadCount":11,"UnixTimestamp":1643825816},{"DownloadCount":10,"UnixTimestamp":1643822615},{"DownloadCount":9,"UnixTimestamp":1643820665},{"DownloadCount":8,"UnixTimestamp":1643813610},{"DownloadCount":7,"UnixTimestamp":1643812913},{"DownloadCount":6,"UnixTimestamp":1643811682},{"DownloadCount":5,"UnixTimestamp":1643808742},{"DownloadCount":4,"UnixTimestamp":1643806057},{"DownloadCount":3,"UnixTimestamp":1643801695},{"DownloadCount":2,"UnixTimestamp":1643800924},{"DownloadCount":2,"UnixTimestamp":1643800924}]