[{"DownloadCount":11739,"UnixTimestamp":1651984197},{"DownloadCount":11714,"UnixTimestamp":1651947620},{"DownloadCount":11692,"UnixTimestamp":1651894978},{"DownloadCount":11672,"UnixTimestamp":1651835450},{"DownloadCount":11649,"UnixTimestamp":1651767156},{"DownloadCount":11627,"UnixTimestamp":1651726243},{"DownloadCount":11603,"UnixTimestamp":1651685696},{"DownloadCount":11575,"UnixTimestamp":1651639583},{"DownloadCount":11518,"UnixTimestamp":1651592257},{"DownloadCount":11518,"UnixTimestamp":1651592257},{"DownloadCount":11504,"UnixTimestamp":1651471198},{"DownloadCount":11476,"UnixTimestamp":1651425254},{"DownloadCount":11449,"UnixTimestamp":1651374727},{"DownloadCount":11424,"UnixTimestamp":1651322008},{"DownloadCount":11404,"UnixTimestamp":1651277761},{"DownloadCount":11381,"UnixTimestamp":1651221560},{"DownloadCount":11359,"UnixTimestamp":1651180427},{"DownloadCount":11337,"UnixTimestamp":1651127028},{"DownloadCount":11313,"UnixTimestamp":1651077998},{"DownloadCount":11283,"UnixTimestamp":1651007872},{"DownloadCount":11257,"UnixTimestamp":1650937680},{"DownloadCount":11234,"UnixTimestamp":1650906314},{"DownloadCount":11210,"UnixTimestamp":1650858441},{"DownloadCount":11184,"UnixTimestamp":1650819731},{"DownloadCount":11161,"UnixTimestamp":1650787834},{"DownloadCount":11131,"UnixTimestamp":1650748950},{"DownloadCount":11109,"UnixTimestamp":1650716173},{"DownloadCount":11084,"UnixTimestamp":1650685883},{"DownloadCount":11049,"UnixTimestamp":1650656104},{"DownloadCount":11028,"UnixTimestamp":1650593837},{"DownloadCount":11010,"UnixTimestamp":1650536007},{"DownloadCount":10987,"UnixTimestamp":1650458058},{"DownloadCount":10960,"UnixTimestamp":1650374329},{"DownloadCount":10938,"UnixTimestamp":1650275143},{"DownloadCount":10918,"UnixTimestamp":1650218013},{"DownloadCount":10900,"UnixTimestamp":1650184774},{"DownloadCount":10868,"UnixTimestamp":1650141241},{"DownloadCount":10849,"UnixTimestamp":1650100707},{"DownloadCount":10824,"UnixTimestamp":1650057794},{"DownloadCount":10797,"UnixTimestamp":1650018286},{"DownloadCount":10767,"UnixTimestamp":1649943225},{"DownloadCount":10746,"UnixTimestamp":1649878848},{"DownloadCount":10746,"UnixTimestamp":1649878848},{"DownloadCount":10709,"UnixTimestamp":1649790240},{"DownloadCount":10688,"UnixTimestamp":1649750769},{"DownloadCount":10666,"UnixTimestamp":1649714991},{"DownloadCount":10666,"UnixTimestamp":1649714991},{"DownloadCount":10620,"UnixTimestamp":1649629436},{"DownloadCount":10596,"UnixTimestamp":1649606552},{"DownloadCount":10574,"UnixTimestamp":1649559710},{"DownloadCount":10551,"UnixTimestamp":1649517538},{"DownloadCount":10526,"UnixTimestamp":1649471071},{"DownloadCount":10502,"UnixTimestamp":1649392840},{"DownloadCount":10480,"UnixTimestamp":1649319400},{"DownloadCount":10456,"UnixTimestamp":1649251594},{"DownloadCount":10433,"UnixTimestamp":1649173222},{"DownloadCount":10374,"UnixTimestamp":1649110279},{"DownloadCount":10345,"UnixTimestamp":1649056704},{"DownloadCount":10317,"UnixTimestamp":1648995901},{"DownloadCount":10293,"UnixTimestamp":1648912378},{"DownloadCount":10273,"UnixTimestamp":1648860399},{"DownloadCount":10251,"UnixTimestamp":1648778011},{"DownloadCount":10231,"UnixTimestamp":1648696379},{"DownloadCount":10205,"UnixTimestamp":1648638626},{"DownloadCount":10177,"UnixTimestamp":1648589438},{"DownloadCount":10153,"UnixTimestamp":1648526638},{"DownloadCount":10110,"UnixTimestamp":1648449055},{"DownloadCount":10107,"UnixTimestamp":1648358363},{"DownloadCount":10083,"UnixTimestamp":1648293835},{"DownloadCount":10061,"UnixTimestamp":1648188719},{"DownloadCount":10038,"UnixTimestamp":1648098244},{"DownloadCount":10038,"UnixTimestamp":1648098244},{"DownloadCount":9997,"UnixTimestamp":1647936391},{"DownloadCount":9978,"UnixTimestamp":1647874659},{"DownloadCount":9959,"UnixTimestamp":1647801094},{"DownloadCount":9938,"UnixTimestamp":1647740504},{"DownloadCount":9919,"UnixTimestamp":1647687688},{"DownloadCount":9903,"UnixTimestamp":1647636205},{"DownloadCount":9903,"UnixTimestamp":1647636205},{"DownloadCount":9864,"UnixTimestamp":1647545056},{"DownloadCount":9846,"UnixTimestamp":1647461207},{"DownloadCount":9827,"UnixTimestamp":1647351326},{"DownloadCount":9804,"UnixTimestamp":1647241534},{"DownloadCount":9783,"UnixTimestamp":1647195897},{"DownloadCount":9764,"UnixTimestamp":1647141177},{"DownloadCount":9746,"UnixTimestamp":1647086149},{"DownloadCount":9746,"UnixTimestamp":1647086149},{"DownloadCount":9711,"UnixTimestamp":1646975178},{"DownloadCount":9690,"UnixTimestamp":1646903883},{"DownloadCount":9672,"UnixTimestamp":1646797923},{"DownloadCount":9653,"UnixTimestamp":1646732841},{"DownloadCount":9635,"UnixTimestamp":1646664805},{"DownloadCount":9619,"UnixTimestamp":1646606290},{"DownloadCount":9601,"UnixTimestamp":1646563029},{"DownloadCount":9578,"UnixTimestamp":1646512249},{"DownloadCount":9561,"UnixTimestamp":1646481521},{"DownloadCount":9561,"UnixTimestamp":1646481521},{"DownloadCount":9523,"UnixTimestamp":1646379803},{"DownloadCount":9500,"UnixTimestamp":1646339495},{"DownloadCount":9482,"UnixTimestamp":1646292646},{"DownloadCount":9460,"UnixTimestamp":1646199256},{"DownloadCount":9442,"UnixTimestamp":1646142399},{"DownloadCount":9425,"UnixTimestamp":1646098668},{"DownloadCount":9408,"UnixTimestamp":1646053083},{"DownloadCount":9385,"UnixTimestamp":1645985944},{"DownloadCount":9365,"UnixTimestamp":1645943138},{"DownloadCount":9338,"UnixTimestamp":1645911111},{"DownloadCount":9315,"UnixTimestamp":1645884579},{"DownloadCount":9293,"UnixTimestamp":1645851073},{"DownloadCount":9265,"UnixTimestamp":1645810961},{"DownloadCount":9244,"UnixTimestamp":1645740619},{"DownloadCount":9223,"UnixTimestamp":1645672001},{"DownloadCount":9200,"UnixTimestamp":1645632856},{"DownloadCount":9181,"UnixTimestamp":1645598213},{"DownloadCount":9153,"UnixTimestamp":1645565736},{"DownloadCount":9135,"UnixTimestamp":1645531461},{"DownloadCount":9113,"UnixTimestamp":1645497405},{"DownloadCount":9088,"UnixTimestamp":1645452689},{"DownloadCount":9070,"UnixTimestamp":1645388688},{"DownloadCount":9050,"UnixTimestamp":1645332881},{"DownloadCount":9032,"UnixTimestamp":1645279513},{"DownloadCount":9011,"UnixTimestamp":1645230096},{"DownloadCount":8982,"UnixTimestamp":1645153210},{"DownloadCount":8961,"UnixTimestamp":1645036379},{"DownloadCount":8943,"UnixTimestamp":1644985099},{"DownloadCount":8925,"UnixTimestamp":1644939608},{"DownloadCount":8902,"UnixTimestamp":1644886733},{"DownloadCount":8883,"UnixTimestamp":1644839034},{"DownloadCount":8862,"UnixTimestamp":1644781637},{"DownloadCount":8843,"UnixTimestamp":1644727121},{"DownloadCount":8826,"UnixTimestamp":1644675813},{"DownloadCount":8809,"UnixTimestamp":1644629441},{"DownloadCount":8791,"UnixTimestamp":1644593060},{"DownloadCount":8769,"UnixTimestamp":1644543370},{"DownloadCount":8748,"UnixTimestamp":1644477571},{"DownloadCount":8726,"UnixTimestamp":1644417653},{"DownloadCount":8705,"UnixTimestamp":1644372528},{"DownloadCount":8685,"UnixTimestamp":1644319112},{"DownloadCount":8662,"UnixTimestamp":1644270169},{"DownloadCount":8643,"UnixTimestamp":1644229915},{"DownloadCount":8614,"UnixTimestamp":1644188462},{"DownloadCount":8591,"UnixTimestamp":1644164667},{"DownloadCount":8571,"UnixTimestamp":1644135298},{"DownloadCount":8546,"UnixTimestamp":1644115504},{"DownloadCount":8517,"UnixTimestamp":1644091861},{"DownloadCount":8497,"UnixTimestamp":1644075326},{"DownloadCount":8477,"UnixTimestamp":1644052258},{"DownloadCount":8456,"UnixTimestamp":1644016763},{"DownloadCount":8438,"UnixTimestamp":1643996282},{"DownloadCount":8420,"UnixTimestamp":1643949346},{"DownloadCount":8399,"UnixTimestamp":1643911449},{"DownloadCount":8378,"UnixTimestamp":1643855269},{"DownloadCount":8357,"UnixTimestamp":1643805435},{"DownloadCount":8341,"UnixTimestamp":1643753100},{"DownloadCount":8322,"UnixTimestamp":1643694852},{"DownloadCount":8301,"UnixTimestamp":1643662108},{"DownloadCount":8274,"UnixTimestamp":1643628504},{"DownloadCount":8247,"UnixTimestamp":1643593579},{"DownloadCount":8222,"UnixTimestamp":1643573301},{"DownloadCount":8202,"UnixTimestamp":1643553587},{"DownloadCount":8182,"UnixTimestamp":1643528105},{"DownloadCount":8156,"UnixTimestamp":1643507014},{"DownloadCount":8129,"UnixTimestamp":1643490492},{"DownloadCount":8107,"UnixTimestamp":1643464081},{"DownloadCount":8087,"UnixTimestamp":1643419663},{"DownloadCount":8065,"UnixTimestamp":1643363152},{"DownloadCount":8046,"UnixTimestamp":1643322976},{"DownloadCount":8029,"UnixTimestamp":1643286385},{"DownloadCount":8008,"UnixTimestamp":1643243553},{"DownloadCount":7989,"UnixTimestamp":1643184393},{"DownloadCount":7964,"UnixTimestamp":1643135076},{"DownloadCount":7945,"UnixTimestamp":1643080936},{"DownloadCount":7925,"UnixTimestamp":1643029348},{"DownloadCount":7904,"UnixTimestamp":1642980065},{"DownloadCount":7883,"UnixTimestamp":1642958443},{"DownloadCount":7858,"UnixTimestamp":1642927070},{"DownloadCount":7753,"UnixTimestamp":1642840541},{"DownloadCount":7680,"UnixTimestamp":1642781813},{"DownloadCount":7659,"UnixTimestamp":1642731013},{"DownloadCount":7633,"UnixTimestamp":1642697286},{"DownloadCount":7612,"UnixTimestamp":1642653334},{"DownloadCount":7583,"UnixTimestamp":1642625205},{"DownloadCount":7563,"UnixTimestamp":1642607835},{"DownloadCount":7540,"UnixTimestamp":1642577783},{"DownloadCount":7514,"UnixTimestamp":1642536964},{"DownloadCount":7491,"UnixTimestamp":1642491545},{"DownloadCount":7462,"UnixTimestamp":1642460528},{"DownloadCount":7441,"UnixTimestamp":1642434569},{"DownloadCount":7421,"UnixTimestamp":1642386875},{"DownloadCount":7397,"UnixTimestamp":1642358657},{"DownloadCount":7370,"UnixTimestamp":1642341736},{"DownloadCount":7347,"UnixTimestamp":1642313022},{"DownloadCount":7320,"UnixTimestamp":1642279396},{"DownloadCount":7298,"UnixTimestamp":1642249303},{"DownloadCount":7278,"UnixTimestamp":1642218282},{"DownloadCount":7257,"UnixTimestamp":1642189844},{"DownloadCount":7235,"UnixTimestamp":1642144778},{"DownloadCount":7208,"UnixTimestamp":1642092377},{"DownloadCount":7183,"UnixTimestamp":1642041862},{"DownloadCount":7159,"UnixTimestamp":1642007317},{"DownloadCount":7137,"UnixTimestamp":1641968765},{"DownloadCount":7112,"UnixTimestamp":1641933535},{"DownloadCount":7093,"UnixTimestamp":1641901216},{"DownloadCount":7070,"UnixTimestamp":1641850897},{"DownloadCount":7045,"UnixTimestamp":1641814489},{"DownloadCount":7022,"UnixTimestamp":1641774245},{"DownloadCount":6999,"UnixTimestamp":1641742079},{"DownloadCount":6980,"UnixTimestamp":1641711840},{"DownloadCount":6949,"UnixTimestamp":1641678644},{"DownloadCount":6916,"UnixTimestamp":1641661694},{"DownloadCount":6890,"UnixTimestamp":1641620717},{"DownloadCount":6867,"UnixTimestamp":1641572601},{"DownloadCount":6843,"UnixTimestamp":1641522814},{"DownloadCount":6821,"UnixTimestamp":1641473918},{"DownloadCount":6801,"UnixTimestamp":1641409124},{"DownloadCount":6785,"UnixTimestamp":1641354606},{"DownloadCount":6762,"UnixTimestamp":1641260046},{"DownloadCount":6739,"UnixTimestamp":1641170723},{"DownloadCount":6718,"UnixTimestamp":1641130630},{"DownloadCount":6699,"UnixTimestamp":1641088564},{"DownloadCount":6679,"UnixTimestamp":1641047813},{"DownloadCount":6659,"UnixTimestamp":1640973858},{"DownloadCount":6642,"UnixTimestamp":1640891071},{"DownloadCount":6625,"UnixTimestamp":1640836060},{"DownloadCount":6600,"UnixTimestamp":1640767432},{"DownloadCount":6579,"UnixTimestamp":1640720810},{"DownloadCount":6560,"UnixTimestamp":1640673567},{"DownloadCount":6538,"UnixTimestamp":1640628587},{"DownloadCount":6511,"UnixTimestamp":1640571519},{"DownloadCount":6488,"UnixTimestamp":1640533248},{"DownloadCount":6467,"UnixTimestamp":1640492903},{"DownloadCount":6446,"UnixTimestamp":1640429818},{"DownloadCount":6421,"UnixTimestamp":1640376199},{"DownloadCount":6402,"UnixTimestamp":1640326551},{"DownloadCount":6381,"UnixTimestamp":1640270321},{"DownloadCount":6361,"UnixTimestamp":1640212286},{"DownloadCount":6343,"UnixTimestamp":1640148631},{"DownloadCount":6328,"UnixTimestamp":1640091007},{"DownloadCount":6309,"UnixTimestamp":1640042927},{"DownloadCount":6286,"UnixTimestamp":1640008094},{"DownloadCount":6266,"UnixTimestamp":1639947865},{"DownloadCount":6246,"UnixTimestamp":1639884365},{"DownloadCount":6226,"UnixTimestamp":1639818747},{"DownloadCount":6205,"UnixTimestamp":1639684113},{"DownloadCount":6184,"UnixTimestamp":1639557043},{"DownloadCount":6161,"UnixTimestamp":1639468742},{"DownloadCount":6141,"UnixTimestamp":1639352689},{"DownloadCount":6121,"UnixTimestamp":1639275012},{"DownloadCount":6101,"UnixTimestamp":1639190392},{"DownloadCount":6080,"UnixTimestamp":1639119210},{"DownloadCount":6063,"UnixTimestamp":1639045902},{"DownloadCount":6043,"UnixTimestamp":1638988211},{"DownloadCount":6021,"UnixTimestamp":1638879149},{"DownloadCount":6002,"UnixTimestamp":1638790354},{"DownloadCount":5985,"UnixTimestamp":1638741792},{"DownloadCount":5964,"UnixTimestamp":1638716109},{"DownloadCount":5946,"UnixTimestamp":1638680185},{"DownloadCount":5929,"UnixTimestamp":1638648083},{"DownloadCount":5903,"UnixTimestamp":1638620819},{"DownloadCount":5884,"UnixTimestamp":1638584017},{"DownloadCount":5860,"UnixTimestamp":1638551743},{"DownloadCount":5840,"UnixTimestamp":1638442743},{"DownloadCount":5819,"UnixTimestamp":1638337901},{"DownloadCount":5797,"UnixTimestamp":1638275410},{"DownloadCount":5779,"UnixTimestamp":1638231255},{"DownloadCount":5760,"UnixTimestamp":1638201562},{"DownloadCount":5737,"UnixTimestamp":1638168937},{"DownloadCount":5714,"UnixTimestamp":1638134553},{"DownloadCount":5693,"UnixTimestamp":1638103314},{"DownloadCount":5669,"UnixTimestamp":1638058945},{"DownloadCount":5642,"UnixTimestamp":1638018339},{"DownloadCount":5616,"UnixTimestamp":1637952737},{"DownloadCount":5597,"UnixTimestamp":1637848840},{"DownloadCount":5580,"UnixTimestamp":1637784210},{"DownloadCount":5560,"UnixTimestamp":1637740298},{"DownloadCount":5539,"UnixTimestamp":1637636173},{"DownloadCount":5517,"UnixTimestamp":1637515353},{"DownloadCount":5496,"UnixTimestamp":1637419621},{"DownloadCount":5477,"UnixTimestamp":1637357951},{"DownloadCount":5461,"UnixTimestamp":1637289474},{"DownloadCount":5444,"UnixTimestamp":1637204680},{"DownloadCount":5428,"UnixTimestamp":1637073306},{"DownloadCount":5410,"UnixTimestamp":1636978918},{"DownloadCount":5389,"UnixTimestamp":1636868659},{"DownloadCount":5369,"UnixTimestamp":1636800019},{"DownloadCount":5351,"UnixTimestamp":1636706154},{"DownloadCount":5334,"UnixTimestamp":1636588301},{"DownloadCount":5316,"UnixTimestamp":1636481622},{"DownloadCount":5293,"UnixTimestamp":1636343146},{"DownloadCount":5274,"UnixTimestamp":1636286517},{"DownloadCount":5254,"UnixTimestamp":1636233323},{"DownloadCount":5235,"UnixTimestamp":1636189149},{"DownloadCount":5219,"UnixTimestamp":1636139704},{"DownloadCount":5199,"UnixTimestamp":1636083062},{"DownloadCount":5181,"UnixTimestamp":1635992999},{"DownloadCount":5164,"UnixTimestamp":1635923380},{"DownloadCount":5141,"UnixTimestamp":1635871767},{"DownloadCount":5115,"UnixTimestamp":1635819582},{"DownloadCount":5092,"UnixTimestamp":1635780254},{"DownloadCount":5071,"UnixTimestamp":1635735098},{"DownloadCount":5046,"UnixTimestamp":1635704479},{"DownloadCount":5026,"UnixTimestamp":1635681832},{"DownloadCount":5007,"UnixTimestamp":1635655196},{"DownloadCount":4980,"UnixTimestamp":1635625084},{"DownloadCount":4959,"UnixTimestamp":1635586260},{"DownloadCount":4937,"UnixTimestamp":1635537730},{"DownloadCount":4913,"UnixTimestamp":1635463536},{"DownloadCount":4892,"UnixTimestamp":1635390690},{"DownloadCount":4872,"UnixTimestamp":1635353653},{"DownloadCount":4849,"UnixTimestamp":1635308096},{"DownloadCount":4829,"UnixTimestamp":1635278081},{"DownloadCount":4809,"UnixTimestamp":1635234766},{"DownloadCount":4778,"UnixTimestamp":1635193472},{"DownloadCount":4754,"UnixTimestamp":1635165628},{"DownloadCount":4728,"UnixTimestamp":1635110185},{"DownloadCount":4706,"UnixTimestamp":1635059346},{"DownloadCount":4683,"UnixTimestamp":1635020572},{"DownloadCount":4665,"UnixTimestamp":1634994069},{"DownloadCount":4641,"UnixTimestamp":1634952785},{"DownloadCount":4615,"UnixTimestamp":1634885514},{"DownloadCount":4589,"UnixTimestamp":1634850406},{"DownloadCount":4567,"UnixTimestamp":1634785832},{"DownloadCount":4538,"UnixTimestamp":1634737978},{"DownloadCount":4510,"UnixTimestamp":1634669465},{"DownloadCount":4485,"UnixTimestamp":1634603175},{"DownloadCount":4459,"UnixTimestamp":1634561240},{"DownloadCount":4437,"UnixTimestamp":1634493070},{"DownloadCount":4416,"UnixTimestamp":1634416844},{"DownloadCount":4387,"UnixTimestamp":1634347090},{"DownloadCount":4355,"UnixTimestamp":1634298356},{"DownloadCount":4186,"UnixTimestamp":1634221473},{"DownloadCount":4145,"UnixTimestamp":1634152417},{"DownloadCount":4010,"UnixTimestamp":1633630640},{"DownloadCount":3820,"UnixTimestamp":1632938135},{"DownloadCount":3801,"UnixTimestamp":1632908960},{"DownloadCount":3784,"UnixTimestamp":1632870558},{"DownloadCount":3768,"UnixTimestamp":1632798329},{"DownloadCount":3740,"UnixTimestamp":1632550374},{"DownloadCount":3689,"UnixTimestamp":1631953346},{"DownloadCount":3671,"UnixTimestamp":1631702250},{"DownloadCount":3653,"UnixTimestamp":1631462426},{"DownloadCount":3634,"UnixTimestamp":1631243185},{"DownloadCount":3617,"UnixTimestamp":1631028786},{"DownloadCount":3601,"UnixTimestamp":1630883679},{"DownloadCount":3584,"UnixTimestamp":1630676357},{"DownloadCount":3563,"UnixTimestamp":1630395624},{"DownloadCount":3545,"UnixTimestamp":1630187690},{"DownloadCount":3528,"UnixTimestamp":1630015325},{"DownloadCount":3507,"UnixTimestamp":1629795311},{"DownloadCount":3489,"UnixTimestamp":1629668111},{"DownloadCount":3466,"UnixTimestamp":1629538019},{"DownloadCount":3448,"UnixTimestamp":1629326541},{"DownloadCount":3429,"UnixTimestamp":1629159068},{"DownloadCount":3410,"UnixTimestamp":1628957475},{"DownloadCount":3388,"UnixTimestamp":1628771450},{"DownloadCount":3367,"UnixTimestamp":1628628432},{"DownloadCount":3342,"UnixTimestamp":1628488991},{"DownloadCount":3325,"UnixTimestamp":1628279527},{"DownloadCount":3309,"UnixTimestamp":1628148738},{"DownloadCount":3291,"UnixTimestamp":1628035789},{"DownloadCount":3272,"UnixTimestamp":1627922246},{"DownloadCount":3250,"UnixTimestamp":1627842948},{"DownloadCount":3231,"UnixTimestamp":1627782913},{"DownloadCount":3213,"UnixTimestamp":1627702208},{"DownloadCount":3195,"UnixTimestamp":1627582531},{"DownloadCount":3177,"UnixTimestamp":1627424319},{"DownloadCount":3161,"UnixTimestamp":1627158674},{"DownloadCount":3144,"UnixTimestamp":1626849787},{"DownloadCount":3127,"UnixTimestamp":1626644286},{"DownloadCount":3109,"UnixTimestamp":1626547168},{"DownloadCount":3093,"UnixTimestamp":1626456382},{"DownloadCount":3073,"UnixTimestamp":1626236692},{"DownloadCount":3056,"UnixTimestamp":1626101391},{"DownloadCount":3039,"UnixTimestamp":1625924416},{"DownloadCount":3016,"UnixTimestamp":1625812170},{"DownloadCount":2996,"UnixTimestamp":1625701919},{"DownloadCount":2977,"UnixTimestamp":1625613228},{"DownloadCount":2957,"UnixTimestamp":1625516889},{"DownloadCount":2942,"UnixTimestamp":1625350977},{"DownloadCount":2923,"UnixTimestamp":1625191903},{"DownloadCount":2905,"UnixTimestamp":1625070054},{"DownloadCount":2888,"UnixTimestamp":1624874465},{"DownloadCount":2871,"UnixTimestamp":1624762509},{"DownloadCount":2854,"UnixTimestamp":1624637964},{"DownloadCount":2835,"UnixTimestamp":1624522992},{"DownloadCount":2813,"UnixTimestamp":1624347328},{"DownloadCount":2794,"UnixTimestamp":1624155353},{"DownloadCount":2771,"UnixTimestamp":1623834346},{"DownloadCount":2750,"UnixTimestamp":1623614967},{"DownloadCount":2733,"UnixTimestamp":1623389329},{"DownloadCount":2711,"UnixTimestamp":1623143426},{"DownloadCount":2685,"UnixTimestamp":1622956353},{"DownloadCount":2660,"UnixTimestamp":1622776282},{"DownloadCount":2639,"UnixTimestamp":1622553840},{"DownloadCount":2606,"UnixTimestamp":1622297537},{"DownloadCount":2586,"UnixTimestamp":1622122587},{"DownloadCount":2563,"UnixTimestamp":1621950671},{"DownloadCount":2541,"UnixTimestamp":1621786492},{"DownloadCount":2516,"UnixTimestamp":1621700529},{"DownloadCount":2495,"UnixTimestamp":1621584173},{"DownloadCount":2479,"UnixTimestamp":1621405032},{"DownloadCount":2462,"UnixTimestamp":1621230456},{"DownloadCount":2444,"UnixTimestamp":1621042237},{"DownloadCount":2423,"UnixTimestamp":1620773379},{"DownloadCount":2406,"UnixTimestamp":1620601856},{"DownloadCount":2388,"UnixTimestamp":1620462349},{"DownloadCount":2372,"UnixTimestamp":1620188188},{"DownloadCount":2354,"UnixTimestamp":1619891658},{"DownloadCount":2332,"UnixTimestamp":1619734908},{"DownloadCount":2314,"UnixTimestamp":1619558085},{"DownloadCount":2304,"UnixTimestamp":1619368108},{"DownloadCount":2303,"UnixTimestamp":1619230720},{"DownloadCount":2285,"UnixTimestamp":1618947188},{"DownloadCount":2267,"UnixTimestamp":1618741525},{"DownloadCount":2250,"UnixTimestamp":1618587021},{"DownloadCount":2235,"UnixTimestamp":1618392665},{"DownloadCount":2220,"UnixTimestamp":1618203911},{"DownloadCount":2201,"UnixTimestamp":1618113967},{"DownloadCount":2182,"UnixTimestamp":1617987091},{"DownloadCount":2166,"UnixTimestamp":1617867716},{"DownloadCount":2148,"UnixTimestamp":1617668562},{"DownloadCount":2128,"UnixTimestamp":1617518088},{"DownloadCount":2111,"UnixTimestamp":1617419567},{"DownloadCount":2094,"UnixTimestamp":1617314562},{"DownloadCount":2077,"UnixTimestamp":1617214240},{"DownloadCount":2058,"UnixTimestamp":1617066357},{"DownloadCount":2041,"UnixTimestamp":1616904302},{"DownloadCount":2022,"UnixTimestamp":1616772687},{"DownloadCount":2001,"UnixTimestamp":1616525867},{"DownloadCount":1984,"UnixTimestamp":1616355646},{"DownloadCount":1966,"UnixTimestamp":1616098660},{"DownloadCount":1944,"UnixTimestamp":1615894365},{"DownloadCount":1925,"UnixTimestamp":1615679095},{"DownloadCount":1903,"UnixTimestamp":1615517050},{"DownloadCount":1884,"UnixTimestamp":1615356468},{"DownloadCount":1866,"UnixTimestamp":1615167858},{"DownloadCount":1848,"UnixTimestamp":1614957410},{"DownloadCount":1831,"UnixTimestamp":1614819056},{"DownloadCount":1815,"UnixTimestamp":1614661446},{"DownloadCount":1796,"UnixTimestamp":1614481222},{"DownloadCount":1774,"UnixTimestamp":1614392450},{"DownloadCount":1758,"UnixTimestamp":1614268203},{"DownloadCount":1742,"UnixTimestamp":1614031301},{"DownloadCount":1727,"UnixTimestamp":1613877506},{"DownloadCount":1707,"UnixTimestamp":1613731467},{"DownloadCount":1687,"UnixTimestamp":1613539474},{"DownloadCount":1668,"UnixTimestamp":1613380691},{"DownloadCount":1651,"UnixTimestamp":1613181361},{"DownloadCount":1635,"UnixTimestamp":1612926161},{"DownloadCount":1619,"UnixTimestamp":1612744722},{"DownloadCount":1603,"UnixTimestamp":1612463115},{"DownloadCount":1583,"UnixTimestamp":1612167320},{"DownloadCount":1562,"UnixTimestamp":1612005122},{"DownloadCount":1542,"UnixTimestamp":1611744036},{"DownloadCount":1520,"UnixTimestamp":1611452461},{"DownloadCount":1501,"UnixTimestamp":1611139075},{"DownloadCount":1482,"UnixTimestamp":1610862912},{"DownloadCount":1460,"UnixTimestamp":1610697928},{"DownloadCount":1439,"UnixTimestamp":1610516819},{"DownloadCount":1420,"UnixTimestamp":1610281598},{"DownloadCount":1404,"UnixTimestamp":1610084713},{"DownloadCount":1386,"UnixTimestamp":1609781204},{"DownloadCount":1369,"UnixTimestamp":1609580052},{"DownloadCount":1348,"UnixTimestamp":1609371927},{"DownloadCount":1329,"UnixTimestamp":1609168855},{"DownloadCount":1309,"UnixTimestamp":1608994878},{"DownloadCount":1291,"UnixTimestamp":1608846960},{"DownloadCount":1273,"UnixTimestamp":1608649593},{"DownloadCount":1254,"UnixTimestamp":1608516575},{"DownloadCount":1235,"UnixTimestamp":1608345875},{"DownloadCount":1217,"UnixTimestamp":1608073782},{"DownloadCount":1200,"UnixTimestamp":1607748022},{"DownloadCount":1182,"UnixTimestamp":1607320243},{"DownloadCount":1165,"UnixTimestamp":1607039406},{"DownloadCount":1146,"UnixTimestamp":1606810702},{"DownloadCount":1129,"UnixTimestamp":1606616492},{"DownloadCount":1113,"UnixTimestamp":1606460410},{"DownloadCount":1096,"UnixTimestamp":1606231454},{"DownloadCount":1080,"UnixTimestamp":1605984255},{"DownloadCount":1064,"UnixTimestamp":1605709325},{"DownloadCount":1048,"UnixTimestamp":1605444424},{"DownloadCount":1032,"UnixTimestamp":1605214183},{"DownloadCount":1013,"UnixTimestamp":1604948372},{"DownloadCount":996,"UnixTimestamp":1604587067},{"DownloadCount":978,"UnixTimestamp":1604352885},{"DownloadCount":960,"UnixTimestamp":1604114118},{"DownloadCount":944,"UnixTimestamp":1603911226},{"DownloadCount":928,"UnixTimestamp":1603656891},{"DownloadCount":910,"UnixTimestamp":1603551396},{"DownloadCount":886,"UnixTimestamp":1603364605},{"DownloadCount":867,"UnixTimestamp":1602958536},{"DownloadCount":848,"UnixTimestamp":1602673296},{"DownloadCount":832,"UnixTimestamp":1602469057},{"DownloadCount":813,"UnixTimestamp":1602342335},{"DownloadCount":798,"UnixTimestamp":1601979147},{"DownloadCount":782,"UnixTimestamp":1601582209},{"DownloadCount":767,"UnixTimestamp":1601152854},{"DownloadCount":748,"UnixTimestamp":1600946997},{"DownloadCount":732,"UnixTimestamp":1600570206},{"DownloadCount":714,"UnixTimestamp":1600177514},{"DownloadCount":695,"UnixTimestamp":1599747191},{"DownloadCount":676,"UnixTimestamp":1599373470},{"DownloadCount":652,"UnixTimestamp":1599024693},{"DownloadCount":634,"UnixTimestamp":1598858113},{"DownloadCount":616,"UnixTimestamp":1598639634},{"DownloadCount":599,"UnixTimestamp":1598453439},{"DownloadCount":581,"UnixTimestamp":1598190793},{"DownloadCount":562,"UnixTimestamp":1597797248},{"DownloadCount":544,"UnixTimestamp":1597583935},{"DownloadCount":526,"UnixTimestamp":1597412890},{"DownloadCount":510,"UnixTimestamp":1597238864},{"DownloadCount":492,"UnixTimestamp":1597045985},{"DownloadCount":466,"UnixTimestamp":1596857091},{"DownloadCount":438,"UnixTimestamp":1596475761},{"DownloadCount":422,"UnixTimestamp":1596139060},{"DownloadCount":402,"UnixTimestamp":1595944156},{"DownloadCount":384,"UnixTimestamp":1595692403},{"DownloadCount":366,"UnixTimestamp":1595403378},{"DownloadCount":348,"UnixTimestamp":1595117873},{"DownloadCount":331,"UnixTimestamp":1594755920},{"DownloadCount":315,"UnixTimestamp":1594526640},{"DownloadCount":298,"UnixTimestamp":1594286228},{"DownloadCount":282,"UnixTimestamp":1594033993},{"DownloadCount":263,"UnixTimestamp":1593903433},{"DownloadCount":244,"UnixTimestamp":1593716771},{"DownloadCount":225,"UnixTimestamp":1593466762},{"DownloadCount":205,"UnixTimestamp":1593317627},{"DownloadCount":188,"UnixTimestamp":1593014651},{"DownloadCount":172,"UnixTimestamp":1592740395},{"DownloadCount":154,"UnixTimestamp":1592328223},{"DownloadCount":136,"UnixTimestamp":1590823245},{"DownloadCount":118,"UnixTimestamp":1590034039},{"DownloadCount":118,"UnixTimestamp":1590034039}]